pypi_hello_world/__init__.py
pypi_hello_world-1.0.dist-info/METADATA
pypi_hello_world-1.0.dist-info/WHEEL
pypi_hello_world-1.0.dist-info/top_level.txt
pypi_hello_world-1.0.dist-info/RECORD
