Metadata-Version: 2.1
Name: pypi-hello-world
Version: 1.0
Summary: My PyPi hello world
Home-page: https://github.com/pasiasty/pypi_hello_world
Author: Mariusz Pasek
Author-email: pasiasty@gmail.com
License: MIT
Platform: UNKNOWN
